README.md
setup.py
microBeesPy/__init__.py
microBeesPy/bee.py
microBeesPy/exceptions.py
microBeesPy/microbees.py
microBeesPy/mqtt.py
microBeesPy/profile.py
microBeesPy.egg-info/PKG-INFO
microBeesPy.egg-info/SOURCES.txt
microBeesPy.egg-info/dependency_links.txt
microBeesPy.egg-info/not-zip-safe
microBeesPy.egg-info/requires.txt
microBeesPy.egg-info/top_level.txt
tests/__init__.py
tests/test.py
tests/test_myfunctions.py