Metadata-Version: 2.1
Name: microBeesPy
Version: 0.3.4
Summary: microBees Python Library
Home-page: https://github.com/microBeesTech/pythonSDK/
Author: @microBeesTech
Author-email: developers@microbees.com
License: MIT
Keywords: microbees
Platform: any
Requires-Python: >=3.6
